README.md
setup.py
mylib_ual/__init__.py
mylib_ual/mylib.py
mylib_ual.egg-info/PKG-INFO
mylib_ual.egg-info/SOURCES.txt
mylib_ual.egg-info/dependency_links.txt
mylib_ual.egg-info/top_level.txt