Metadata-Version: 2.1
Name: mylib-ual
Version: 1.4.2
Summary: A web tip of Django
Home-page: 
Author: hellok
Author-email: iz1241@163.com
Keywords: mylib
Classifier: Programming Language :: Python :: 3.12
Classifier: Intended Audience :: Developers
Classifier: License :: OSI Approved :: MIT License
